{
  "annotations": {
    "list": [
      {
        "$$hashKey": "object:32",
        "builtIn": 1,
        "datasource": "-- Grafana --",
        "enable": true,
        "hide": true,
        "iconColor": "rgba(0, 211, 255, 1)",
        "name": "Annotations & Alerts",
        "type": "dashboard"
      }
    ]
  },
  "editable": true,
  "gnetId": null,
  "graphTooltip": 0,
  "id": 1,
  "links": [],
  "panels": [
    {
      "aliasColors": {},
      "bars": false,
      "dashLength": 10,
      "dashes": false,
      "datasource": null,
      "fill": 1,
      "fillGradient": 0,
      "gridPos": {
        "h": 9,
        "w": 10,
        "x": 0,
        "y": 0
      },
      "hiddenSeries": false,
      "id": 2,
      "legend": {
        "avg": false,
        "current": false,
        "max": false,
        "min": false,
        "show": true,
        "total": false,
        "values": false
      },
      "lines": true,
      "linewidth": 1,
      "nullPointMode": "null",
      "options": {
        "dataLinks": []
      },
      "percentage": false,
      "pointradius": 2,
      "points": false,
      "renderer": "flot",
      "seriesOverrides": [],
      "spaceLength": 10,
      "stack": false,
      "steppedLine": false,
      "targets": [
        {
          "expr": "telraam_team_lapcount",
          "interval": "",
          "legendFormat": "",
          "refId": "A"
        }
      ],
      "thresholds": [],
      "timeFrom": null,
      "timeRegions": [],
      "timeShift": null,
      "title": "Lap graph",
      "tooltip": {
        "shared": true,
        "sort": 0,
        "value_type": "individual"
      },
      "type": "graph",
      "xaxis": {
        "buckets": null,
        "mode": "time",
        "name": null,
        "show": true,
        "values": []
      },
      "yaxes": [
        {
          "$$hashKey": "object:89",
          "format": "short",
          "label": "",
          "logBase": 1,
          "max": null,
          "min": null,
          "show": true
        },
        {
          "$$hashKey": "object:90",
          "format": "short",
          "label": null,
          "logBase": 1,
          "max": null,
          "min": null,
          "show": true
        }
      ],
      "yaxis": {
        "align": false,
        "alignLevel": null
      }
    },
    {
      "columns": [],
      "datasource": null,
      "fontSize": "100%",
      "gridPos": {
        "h": 21,
        "w": 7,
        "x": 10,
        "y": 0
      },
      "id": 4,
      "pageSize": null,
      "showHeader": true,
      "sort": {
        "col": 6,
        "desc": true
      },
      "styles": [
        {
          "$$hashKey": "object:259",
          "alias": "Last event",
          "align": "auto",
          "dateFormat": "YYYY-MM-DD HH:mm:ss",
          "link": false,
          "pattern": "Time",
          "type": "date"
        },
        {
          "$$hashKey": "object:1997",
          "alias": "",
          "align": "auto",
          "colorMode": null,
          "colors": [
            "rgba(245, 54, 54, 0.9)",
            "rgba(237, 129, 40, 0.89)",
            "rgba(50, 172, 45, 0.97)"
          ],
          "dateFormat": "YYYY-MM-DD HH:mm:ss",
          "decimals": 2,
          "mappingType": 1,
          "pattern": "__name__",
          "thresholds": [],
          "type": "hidden",
          "unit": "short"
        },
        {
          "$$hashKey": "object:2053",
          "alias": "",
          "align": "auto",
          "colorMode": null,
          "colors": [
            "rgba(245, 54, 54, 0.9)",
            "rgba(237, 129, 40, 0.89)",
            "rgba(50, 172, 45, 0.97)"
          ],
          "dateFormat": "YYYY-MM-DD HH:mm:ss",
          "decimals": 2,
          "mappingType": 1,
          "pattern": "instance",
          "thresholds": [],
          "type": "hidden",
          "unit": "short"
        },
        {
          "$$hashKey": "object:2087",
          "alias": "",
          "align": "auto",
          "colorMode": null,
          "colors": [
            "rgba(245, 54, 54, 0.9)",
            "rgba(237, 129, 40, 0.89)",
            "rgba(50, 172, 45, 0.97)"
          ],
          "dateFormat": "YYYY-MM-DD HH:mm:ss",
          "decimals": 2,
          "mappingType": 1,
          "pattern": "job",
          "thresholds": [],
          "type": "hidden",
          "unit": "short"
        },
        {
          "$$hashKey": "object:2139",
          "alias": "",
          "align": "auto",
          "colorMode": null,
          "colors": [
            "rgba(245, 54, 54, 0.9)",
            "rgba(237, 129, 40, 0.89)",
            "rgba(50, 172, 45, 0.97)"
          ],
          "dateFormat": "YYYY-MM-DD HH:mm:ss",
          "decimals": 2,
          "mappingType": 1,
          "pattern": "team_id",
          "thresholds": [],
          "type": "hidden",
          "unit": "short"
        },
        {
          "$$hashKey": "object:2524",
          "alias": "",
          "align": "auto",
          "colorMode": null,
          "colors": [
            "rgba(245, 54, 54, 0.9)",
            "rgba(237, 129, 40, 0.89)",
            "rgba(50, 172, 45, 0.97)"
          ],
          "dateFormat": "YYYY-MM-DD HH:mm:ss",
          "decimals": 0,
          "mappingType": 1,
          "pattern": "Value",
          "thresholds": [],
          "type": "number",
          "unit": "short"
        },
        {
          "$$hashKey": "object:3840",
          "alias": "Team name",
          "align": "auto",
          "colorMode": null,
          "colors": [
            "rgba(245, 54, 54, 0.9)",
            "rgba(237, 129, 40, 0.89)",
            "rgba(50, 172, 45, 0.97)"
          ],
          "dateFormat": "YYYY-MM-DD HH:mm:ss",
          "decimals": 2,
          "mappingType": 1,
          "pattern": "team_name",
          "thresholds": [],
          "type": "number",
          "unit": "short"
        },
        {
          "$$hashKey": "object:260",
          "alias": "",
          "align": "right",
          "colorMode": null,
          "colors": [
            "rgba(245, 54, 54, 0.9)",
            "rgba(237, 129, 40, 0.89)",
            "rgba(50, 172, 45, 0.97)"
          ],
          "decimals": 2,
          "pattern": "/.*/",
          "thresholds": [],
          "type": "number",
          "unit": "short"
        }
      ],
      "targets": [
        {
          "expr": "telraam_team_lapcount",
          "format": "table",
          "instant": true,
          "interval": "",
          "intervalFactor": 1,
          "legendFormat": "",
          "refId": "A"
        }
      ],
      "timeFrom": null,
      "timeShift": null,
      "title": "Current laps",
      "transform": "table",
      "type": "table"
    },
    {
      "columns": [],
      "datasource": null,
      "fontSize": "100%",
      "gridPos": {
        "h": 7,
        "w": 7,
        "x": 17,
        "y": 0
      },
      "id": 6,
      "pageSize": null,
      "showHeader": true,
      "sort": {
        "col": 0,
        "desc": true
      },
      "styles": [
        {
          "$$hashKey": "object:15292",
          "alias": "Time",
          "align": "auto",
          "dateFormat": "YYYY-MM-DD HH:mm:ss",
          "pattern": "Time",
          "type": "date"
        },
        {
          "$$hashKey": "object:16403",
          "alias": "",
          "align": "auto",
          "colorMode": null,
          "colors": [
            "rgba(245, 54, 54, 0.9)",
            "rgba(237, 129, 40, 0.89)",
            "rgba(50, 172, 45, 0.97)"
          ],
          "dateFormat": "YYYY-MM-DD HH:mm:ss",
          "decimals": 2,
          "mappingType": 1,
          "pattern": "instance",
          "thresholds": [],
          "type": "hidden",
          "unit": "short"
        },
        {
          "$$hashKey": "object:16447",
          "alias": "",
          "align": "auto",
          "colorMode": null,
          "colors": [
            "rgba(245, 54, 54, 0.9)",
            "rgba(237, 129, 40, 0.89)",
            "rgba(50, 172, 45, 0.97)"
          ],
          "dateFormat": "YYYY-MM-DD HH:mm:ss",
          "decimals": 2,
          "mappingType": 1,
          "pattern": "job",
          "thresholds": [],
          "type": "hidden",
          "unit": "short"
        },
        {
          "$$hashKey": "object:16474",
          "alias": "Beacon ID",
          "align": "auto",
          "colorMode": null,
          "colors": [
            "rgba(245, 54, 54, 0.9)",
            "rgba(237, 129, 40, 0.89)",
            "rgba(50, 172, 45, 0.97)"
          ],
          "dateFormat": "YYYY-MM-DD HH:mm:ss",
          "decimals": 0,
          "mappingType": 1,
          "pattern": "beacon_id",
          "thresholds": [],
          "type": "number",
          "unit": "short"
        },
        {
          "$$hashKey": "object:16529",
          "alias": "Tijd sinds laatste detectie (s)",
          "align": "auto",
          "colorMode": "cell",
          "colors": [
            "rgba(50, 172, 45, 0.97)",
            "rgba(237, 129, 40, 0.89)",
            "rgba(245, 54, 54, 0.9)"
          ],
          "dateFormat": "YYYY-MM-DD HH:mm:ss",
          "decimals": 2,
          "mappingType": 1,
          "pattern": "Value",
          "preserveFormat": false,
          "sanitize": false,
          "thresholds": [
            "50",
            "60"
          ],
          "type": "string",
          "unit": "short",
          "valueMaps": []
        },
        {
          "$$hashKey": "object:15293",
          "alias": "",
          "align": "right",
          "colorMode": null,
          "colors": [
            "rgba(245, 54, 54, 0.9)",
            "rgba(237, 129, 40, 0.89)",
            "rgba(50, 172, 45, 0.97)"
          ],
          "decimals": 2,
          "pattern": "/.*/",
          "thresholds": [],
          "type": "number",
          "unit": "short"
        }
      ],
      "targets": [
        {
          "expr": "time() - telraam_last_beacon_detection/1000",
          "format": "table",
          "instant": true,
          "interval": "",
          "legendFormat": "",
          "refId": "A"
        }
      ],
      "timeFrom": null,
      "timeShift": null,
      "title": "Laatste detecties voor beacons",
      "transform": "table",
      "type": "table"
    }
  ],
  "refresh": "1s",
  "schemaVersion": 22,
  "style": "dark",
  "tags": [],
  "templating": {
    "list": []
  },
  "time": {
    "from": "now-5m",
    "to": "now"
  },
  "timepicker": {
    "refresh_intervals": [
      "1s",
      " 3s",
      " 5s",
      "10s",
      "30s",
      "1m",
      "5m",
      "15m",
      "30m",
      "1h"
    ]
  },
  "timezone": "",
  "title": "Laps overview",
  "uid": "y9DWmy_Wk",
  "version": 3
}